aetherdb/__init__.py
aetherdb/db.py
aetherdb-0.0.1b1.dist-info/LICENSE
aetherdb-0.0.1b1.dist-info/METADATA
aetherdb-0.0.1b1.dist-info/WHEEL
aetherdb-0.0.1b1.dist-info/top_level.txt
aetherdb-0.0.1b1.dist-info/RECORD
