Metadata-Version: 2.1
Name: aetherdb
Version: 0.0.1b1
Summary: AetherDB is a lightweight document-like database for Python.
Author-email: Dragooonat <59411437+Dragooonat@users.noreply.github.com>
License: Apache-2.0 license
Keywords: database,document,python
Classifier: Programming Language :: Python :: 3
Requires-Python: >=3.10
License-File: LICENSE
